.gitignore
Pipfile
README.md
setup.py
plugin/restsql.tar
plugin/rest-sql-datasource/.gitignore
plugin/rest-sql-datasource/.jscs.json
plugin/rest-sql-datasource/Gruntfile.js
plugin/rest-sql-datasource/LICENSE
plugin/rest-sql-datasource/README.md
plugin/rest-sql-datasource/build-dev.cmd
plugin/rest-sql-datasource/build-dev.sh
plugin/rest-sql-datasource/package-lock.json
plugin/rest-sql-datasource/package.json
plugin/rest-sql-datasource/yarn.lock
plugin/rest-sql-datasource/doc/datasource.md
plugin/rest-sql-datasource/doc/module.md
plugin/rest-sql-datasource/doc/plugin.md
plugin/rest-sql-datasource/doc/query_ctrl.md
plugin/rest-sql-datasource/doc/task.md
plugin/rest-sql-datasource/spec/datasource_spec.js
plugin/rest-sql-datasource/spec/test-main.js
plugin/rest-sql-datasource/src/config_ctrl.js
plugin/rest-sql-datasource/src/datasource.js
plugin/rest-sql-datasource/src/module.js
plugin/rest-sql-datasource/src/plugin.json
plugin/rest-sql-datasource/src/query_ctrl.js
plugin/rest-sql-datasource/src/sql_part.js
plugin/rest-sql-datasource/src/css/query-editor.css
plugin/rest-sql-datasource/src/img/restsql_logo.svg
plugin/rest-sql-datasource/src/partials/annotations.editor.html
plugin/rest-sql-datasource/src/partials/config.html
plugin/rest-sql-datasource/src/partials/query.editor.html
plugin/rest-sql-datasource/src/partials/query.options.html
plugin/restsql-server/.dockerignore
plugin/restsql-server/.gitignore
plugin/restsql-server/Dockerfile
plugin/restsql-server/Pipfile
plugin/restsql-server/README.md
plugin/restsql-server/requirements.txt
plugin/restsql-server/restsqlserver/__init__.py
plugin/restsql-server/restsqlserver/config.py
plugin/restsql-server/restsqlserver/main.py
plugin/restsql-server/restsqlserver/utils.py
restsql/__init__.py
restsql/engine.py
restsql/entry.py
restsql/exception.py
restsql.egg-info/PKG-INFO
restsql.egg-info/SOURCES.txt
restsql.egg-info/dependency_links.txt
restsql.egg-info/requires.txt
restsql.egg-info/top_level.txt
restsql/config/__init__.py
restsql/config/database.py
restsql/config/load.py
restsql/config/table.py
restsql/config/value.py
test/__init__.py
test/query_test.py
