Metadata-Version: 1.2
Name: restsql
Version: 2.0.8
Summary: RestSQL库。用json与数据库交互。
Home-page: https://git.code.oa.com/tencent_cloud_mobile_tools/RestSQL
Author: oliverdding
Author-email: oliverdding@tencent.com
Maintainer: oliverdding
Maintainer-email: oliverdding@tencent.com
License: MIT License
Platform: UNKNOWN
Classifier: Programming Language :: Python
Classifier: License :: OSI Approved :: MIT License
Classifier: Operating System :: OS Independent
